ao3kindle/__init__.py
ao3kindle/ao3kindle.py
ao3kindle-0.1.5.data/scripts/ao3-kindle
ao3kindle-0.1.5.dist-info/LICENSE
ao3kindle-0.1.5.dist-info/METADATA
ao3kindle-0.1.5.dist-info/WHEEL
ao3kindle-0.1.5.dist-info/top_level.txt
ao3kindle-0.1.5.dist-info/RECORD
