Metadata-Version: 2.1
Name: ao3kindle
Version: 0.1.5
Summary: Upload AO3 fanfics to an Amazon Kindle
Home-page: https://github.com/sgsunder/ao3-kindle
Author: Shyam Sunder
Author-email: sgsunder1@gmail.com
License: UNKNOWN
Platform: UNKNOWN
Classifier: Programming Language :: Python :: 3.5
Classifier: License :: OSI Approved :: GNU General Public License v3 (GPLv3)
Classifier: Operating System :: OS Independent
Classifier: Topic :: Utilities
Requires-Python: >=3.5
Requires-Dist: ao3 (>=0.2.0)
Requires-Dist: appdirs (>=1.2.0)
